komoutils/__init__.py
komoutils/core/__init__.py
komoutils/core/base/__init__.py
komoutils/core/base/komo_base.py
komoutils/core/base/publish_queue.py
komoutils/core/encodings/__init__.py
komoutils/core/time/__init__.py
komoutils/db/__init__.py
komoutils/db/mongodb_reader_writer.py
komoutils/logger/__init__.py
komoutils/logger/logger.py
komoutils/logger/struct_logger.py
komoutils-0.0.235.dist-info/METADATA
komoutils-0.0.235.dist-info/WHEEL
komoutils-0.0.235.dist-info/RECORD
